pulp_smart_proxy/__init__.py
pulp_smart_proxy/app/__init__.py
pulp_smart_proxy/app/settings.py
pulp_smart_proxy/app/urls.py
pulp_smart_proxy/app/views.py
pulp_smart_proxy/tests/__init__.py
pulp_smart_proxy/tests/functional/__init__.py
pulp_smart_proxy/tests/functional/api/__init__.py
pulp_smart_proxy/tests/functional/api/test_smart_proxy_api.py
pulp_smart_proxy/tests/performance/__init__.py
pulp_smart_proxy/tests/unit/__init__.py
pulp_smart_proxy-0.3.0.dist-info/licenses/LICENSE
pulp_smart_proxy-0.3.0.dist-info/METADATA
pulp_smart_proxy-0.3.0.dist-info/WHEEL
pulp_smart_proxy-0.3.0.dist-info/entry_points.txt
pulp_smart_proxy-0.3.0.dist-info/top_level.txt
pulp_smart_proxy-0.3.0.dist-info/RECORD
